SmartFramework/__init__.py
SmartFramework/files/__init__.py
SmartFramework/image/__init__.py
SmartFramework/image/image_conversion.py
SmartFramework/serialize/__init__.py
SmartFramework/string/__init__.py
SmartFramework/string/encodings/__init__.py
SmartFramework/string/encodings/ascii_printables.py
SmartFramework/tools/__init__.py
SmartFramework/tools/dictionaries.py
SmartFramework/tools/functions.py
SmartFramework/tools/objects.py
serializejson/__init__.py
serializejson/serialize_parameters.py
serializejson/simple_exemple.py
serializejson/simple_exemple_update.py
serializejson/tools.py
serializejson/plugins/__init__.py
serializejson/plugins/module_name.py
serializejson/plugins/pickle_PyQt5_PySide2.py
serializejson/plugins/serializejson_PyQt5_PySide2.py
serializejson/plugins/serializejson_array.py
serializejson/plugins/serializejson_builtins.py
serializejson/plugins/serializejson_datetime.py
serializejson/plugins/serializejson_numpy.py
serializejson-0.3.2.data/data/CHANGELOG.rst
serializejson-0.3.2.data/data/LICENSE.rst
serializejson-0.3.2.data/data/pyproject.toml
serializejson-0.3.2.dist-info/LICENSE-APACHE.rst
serializejson-0.3.2.dist-info/LICENSE-PATRON.rst
serializejson-0.3.2.dist-info/LICENSE-PROSPERITY.rst
serializejson-0.3.2.dist-info/LICENSE.rst
serializejson-0.3.2.dist-info/METADATA
serializejson-0.3.2.dist-info/WHEEL
serializejson-0.3.2.dist-info/top_level.txt
serializejson-0.3.2.dist-info/RECORD
