Metadata-Version: 2.1
Name: serializejson
Version: 0.3.2
Summary: A python library for fast serialization and deserialization of complex Python objects into JSON.
Home-page: https://github.com/SmartAudioTools/serializejson
Author: Baptiste de La Gorce
Author-email: baptiste.delagorce@smartaudiotools.com
License: Prosperity Public License 3.0.0 and Patron License 1.0.0
Download-URL: https://github.com/SmartAudioTools/serializejson/tarball/master
Project-URL: Documentation, https://smartaudiotools.github.io/serializejson
Project-URL: Funding, https://github.com/sponsors/SmartAudioTools
Project-URL: Source, https://github.com/SmartAudioTools/serializejson
Project-URL: Tracker, https://github.com/SmartAudioTools/serializejson/issues
Keywords: pickle json serialize dump dumps rapidjson base64
Platform: UNKNOWN
Classifier: Development Status :: 3 - Alpha
Classifier: Intended Audience :: Developers
Classifier: License :: Free for non-commercial use
Classifier: Programming Language :: Python :: 3
Classifier: Programming Language :: Python :: 3.7
Classifier: Programming Language :: Python :: 3.8
Classifier: Programming Language :: Python :: 3.9
Requires-Python: >=3
License-File: LICENSE-APACHE.rst
License-File: LICENSE-PATRON.rst
License-File: LICENSE-PROSPERITY.rst
License-File: LICENSE.rst
Requires-Dist: pybase64 (>=1.1.1)
Requires-Dist: python-rapidjson (>=1.0)
Requires-Dist: apply
Requires-Dist: blosc
Requires-Dist: importlib-metadata ; python_version < "3.8"
Provides-Extra: dev
Requires-Dist: pytest ; extra == 'dev'
Requires-Dist: numpy ; extra == 'dev'
Requires-Dist: qtpy ; extra == 'dev'
Requires-Dist: PyQt5 ; extra == 'dev'
Provides-Extra: test
Requires-Dist: pytest ; extra == 'test'
Requires-Dist: numpy ; extra == 'test'
